WagonTestGUI/__init__.py
WagonTestGUI/__main__.py
WagonTestGUI/run_stress_test.py
WagonTestGUI/PythonFiles/GUIWindow.py
WagonTestGUI/PythonFiles/StressTest.py
WagonTestGUI/PythonFiles/TestFailedPopup.py
WagonTestGUI/PythonFiles/__init__.py
WagonTestGUI/PythonFiles/Data/DBSender.py
WagonTestGUI/PythonFiles/Data/DataHolder.py
WagonTestGUI/PythonFiles/Data/__init__.py
WagonTestGUI/PythonFiles/Images/Bethel_Logo.png
WagonTestGUI/PythonFiles/Images/GreenCheckMark.png
WagonTestGUI/PythonFiles/Images/QRimage.png
WagonTestGUI/PythonFiles/Images/RedX.png
WagonTestGUI/PythonFiles/Images/UMN_Logo.png
WagonTestGUI/PythonFiles/Images/__init__.py
WagonTestGUI/PythonFiles/JSONFiles/Current_BERT_JSON.json
WagonTestGUI/PythonFiles/JSONFiles/Current_GenRes_JSON.json
WagonTestGUI/PythonFiles/JSONFiles/Current_IDRes_JSON.json
WagonTestGUI/PythonFiles/JSONFiles/Current_IIC_JSON.json
WagonTestGUI/PythonFiles/JSONFiles/__init__.py
WagonTestGUI/PythonFiles/JSONFiles/storage.json
WagonTestGUI/PythonFiles/Scanner/__init__.py
WagonTestGUI/PythonFiles/Scanner/bin/__init__.py
WagonTestGUI/PythonFiles/Scanner/bin/runScanner
WagonTestGUI/PythonFiles/Scanner/python/__init__.py
WagonTestGUI/PythonFiles/Scanner/python/get_barcodes.py
WagonTestGUI/PythonFiles/Scenes/AddUserScene.py
WagonTestGUI/PythonFiles/Scenes/Inspection1.py
WagonTestGUI/PythonFiles/Scenes/LoginScene.py
WagonTestGUI/PythonFiles/Scenes/ScanScene.py
WagonTestGUI/PythonFiles/Scenes/SidebarScene.py
WagonTestGUI/PythonFiles/Scenes/SplashScene.py
WagonTestGUI/PythonFiles/Scenes/TestInProgressScene.py
WagonTestGUI/PythonFiles/Scenes/TestScene.py
WagonTestGUI/PythonFiles/Scenes/TestSummaryScene.py
WagonTestGUI/PythonFiles/Scenes/__init__.py
WagonTestGUI/PythonFiles/logs/__init__.py
WagonTestGUI/PythonFiles/utils/REQClient.py
WagonTestGUI/PythonFiles/utils/SUBClient.py
WagonTestGUI/PythonFiles/utils/StressScript.py
WagonTestGUI/PythonFiles/utils/__init__.py
WagonTestGUI-1.2.4.dist-info/METADATA
WagonTestGUI-1.2.4.dist-info/WHEEL
WagonTestGUI-1.2.4.dist-info/top_level.txt
WagonTestGUI-1.2.4.dist-info/RECORD
