Metadata-Version: 2.1
Name: WagonTestGUI
Version: 1.2.4
Summary: Python scripts to be located on the user interface computer.
Home-page: https://github.com/UMN-CMS/WagonTestGUI
Author: Garrett Schindler, Andrew Kirzeder, & Bryan Crossman
Author-email: none@gmail.com
License: UNKNOWN
Platform: UNKNOWN
Requires-Dist: numpy
Requires-Dist: matplotlib
Requires-Dist: subprocess
Requires-Dist: socket
Requires-Dist: audioop
Requires-Dist: logging
Requires-Dist: json
